XnatUploadToolDicom
