Metadata-Version: 1.2
Name: XnatUploadToolDicom
Version: 1.0.7.3
Summary: Tool for assisting in uploading dicom data directly to xnat imaging research platform (xnat.org)
Home-page: https://bitbucket.org/radiologics/XnatUploadToolDicom
Author: Brian Holt
Author-email: brian@radiologics.com
License: BSD 3-Clause License
Keywords: xnat
Platform: UNKNOWN
Classifier: Topic :: Scientific/Engineering :: Medical Science Apps.
Classifier: Development Status :: 3 - Alpha
Classifier: Programming Language :: Python :: 2.7
Classifier: Programming Language :: Python :: 2
Requires-Python: >=2.6
